README.rst
setup.py
tgext/__init__.py
tgext.mobilemiddleware.egg-info/PKG-INFO
tgext.mobilemiddleware.egg-info/SOURCES.txt
tgext.mobilemiddleware.egg-info/dependency_links.txt
tgext.mobilemiddleware.egg-info/entry_points.txt
tgext.mobilemiddleware.egg-info/namespace_packages.txt
tgext.mobilemiddleware.egg-info/not-zip-safe
tgext.mobilemiddleware.egg-info/requires.txt
tgext.mobilemiddleware.egg-info/top_level.txt
tgext/mobilemiddleware/__init__.py
tgext/mobilemiddleware/decorators.py
tgext/mobilemiddleware/middleware.py