Metadata-Version: 1.1
Name: tgext.mobilemiddleware
Version: 0.4
Summary: Mobile Middleware utilities for Turbogears 2 detects mobile browsers
Home-page: http://bitbucket.org/_amol_/tgext.mobilemiddleware
Author: Alessandro Molina
Author-email: alessandro.molina@axant.it
License: LGPL
Keywords: turbogears2.extension pylons
Platform: UNKNOWN
Classifier: Environment :: Web Environment
Classifier: Topic :: Software Development :: Libraries :: Python Modules
Classifier: Framework :: TurboGears
